hypermodern_python_2261361010/__init__.py
hypermodern_python_2261361010/console.py
hypermodern_python_2261361010/wikipedia.py
hypermodern_python_2261361010-1.0.5.dist-info/LICENSE
hypermodern_python_2261361010-1.0.5.dist-info/METADATA
hypermodern_python_2261361010-1.0.5.dist-info/WHEEL
hypermodern_python_2261361010-1.0.5.dist-info/entry_points.txt
hypermodern_python_2261361010-1.0.5.dist-info/RECORD
