Metadata-Version: 2.1
Name: hypermodern-python-2261361010
Version: 1.0.5
Summary: The hypermodern Python project
Home-page: https://github.com/PSims/hypermodern-python
License: MIT
Keywords: hypermodern
Author: PSims
Author-email: 6097708+PSims@users.noreply.github.com
Requires-Python: >=3.11,<4.0
Classifier: License :: OSI Approved :: MIT License
Classifier: Programming Language :: Python :: 3
Classifier: Programming Language :: Python :: 3.11
Classifier: Programming Language :: Python :: 3.12
Requires-Dist: click (>=8.1.7,<9.0.0)
Requires-Dist: desert (>=2022.9.22,<2023.0.0)
Requires-Dist: importlib-metadata (>=8.2.0,<9.0.0) ; python_version < "3.8"
Requires-Dist: marshmallow (>=3.21.3,<4.0.0)
Requires-Dist: requests (>=2.32.3,<3.0.0)
Project-URL: Repository, https://github.com/PSims/hypermodern-python
